{
  "updated_at": "2025-12-29T11:40:14.482Z",
  "convert": "EUR",
  "global": {
    "data": {
      "active_cryptocurrencies": 100,
      "markets": null,
      "total_market_cap": {
        "usd": 3061046159540.7866,
        "eur": 2596960951292.808
      },
      "total_volume": {
        "usd": 73753898595.47765,
        "eur": 62572070029.41728
      },
      "market_cap_percentage": {
        "btc": 57.186044556830126
      },
      "market_cap_change_percentage_24h_usd": null,
      "updated_at": 1767008414
    }
  },
  "trending": {
    "coins": [
      {
        "item": {
          "id": "1",
          "name": "Bitcoin",
          "symbol": "btc",
          "market_cap_rank": 1,
          "small": null
        }
      },
      {
        "item": {
          "id": "3",
          "name": "Ethereum",
          "symbol": "eth",
          "market_cap_rank": 2,
          "small": null
        }
      },
      {
        "item": {
          "id": "16",
          "name": "Tether",
          "symbol": "usdt",
          "market_cap_rank": 3,
          "small": null
        }
      },
      {
        "item": {
          "id": "26",
          "name": "BNB",
          "symbol": "bnb",
          "market_cap_rank": 4,
          "small": null
        }
      },
      {
        "item": {
          "id": "5",
          "name": "XRP",
          "symbol": "xrp",
          "market_cap_rank": 5,
          "small": null
        }
      },
      {
        "item": {
          "id": "5487",
          "name": "USDC",
          "symbol": "usdc",
          "market_cap_rank": 6,
          "small": null
        }
      },
      {
        "item": {
          "id": "5663",
          "name": "Solana",
          "symbol": "sol",
          "market_cap_rank": 7,
          "small": null
        }
      },
      {
        "item": {
          "id": "13",
          "name": "TRON",
          "symbol": "trx",
          "market_cap_rank": 8,
          "small": null
        }
      },
      {
        "item": {
          "id": "171882",
          "name": "Lido Staked Ether",
          "symbol": "steth",
          "market_cap_rank": 9,
          "small": null
        }
      }
    ]
  },
  "coins": [
    {
      "id": "1",
      "symbol": "btc",
      "name": "Bitcoin",
      "market_cap_rank": 1,
      "image": null,
      "current_price": 74371.5546226712,
      "market_cap": 1485099246729.785,
      "total_volume": 10629563703.703833,
      "price_change_percentage_1h_in_currency": null,
      "price_change_percentage_24h_in_currency": null,
      "price_change_percentage_7d_in_currency": null,
      "circulating_supply": 19968646,
      "max_supply": 21000000,
      "description": null,
      "homepage": null,
      "explorer": null
    },
    {
      "id": "3",
      "symbol": "eth",
      "name": "Ethereum",
      "market_cap_rank": 2,
      "image": null,
      "current_price": 2512.12743575751,
      "market_cap": 303201087715.99854,
      "total_volume": 6525609778.333188,
      "price_change_percentage_1h_in_currency": null,
      "price_change_percentage_24h_in_currency": null,
      "price_change_percentage_7d_in_currency": null,
      "circulating_supply": 120694947,
      "max_supply": 0,
      "description": null,
      "homepage": null,
      "explorer": null
    },
    {
      "id": "16",
      "symbol": "usdt",
      "name": "Tether",
      "market_cap_rank": 3,
      "image": null,
      "current_price": 0.847438806263698,
      "market_cap": 158324266274.617,
      "total_volume": 26683253429.27401,
      "price_change_percentage_1h_in_currency": null,
      "price_change_percentage_24h_in_currency": null,
      "price_change_percentage_7d_in_currency": null,
      "circulating_supply": 186826783367,
      "max_supply": 0,
      "description": null,
      "homepage": null,
      "explorer": null
    },
    {
      "id": "26",
      "symbol": "bnb",
      "name": "BNB",
      "market_cap_rank": 4,
      "image": null,
      "current_price": 723.7672573922129,
      "market_cap": 99690321809.04355,
      "total_volume": 555235007.4157282,
      "price_change_percentage_1h_in_currency": null,
      "price_change_percentage_24h_in_currency": null,
      "price_change_percentage_7d_in_currency": null,
      "circulating_supply": 137738093,
      "max_supply": 137738093,
      "description": null,
      "homepage": null,
      "explorer": null
    },
    {
      "id": "5",
      "symbol": "xrp",
      "name": "XRP",
      "market_cap_rank": 5,
      "image": null,
      "current_price": 1.5906603085529452,
      "market_cap": 96350978804.66022,
      "total_volume": 860556532.9987466,
      "price_change_percentage_1h_in_currency": null,
      "price_change_percentage_24h_in_currency": null,
      "price_change_percentage_7d_in_currency": null,
      "circulating_supply": 60572944636,
      "max_supply": 100000000000,
      "description": null,
      "homepage": null,
      "explorer": null
    },
    {
      "id": "5487",
      "symbol": "usdc",
      "name": "USDC",
      "market_cap_rank": 6,
      "image": null,
      "current_price": 0.8481944735190261,
      "market_cap": 66666128010.348206,
      "total_volume": 5321214487.267805,
      "price_change_percentage_1h_in_currency": null,
      "price_change_percentage_24h_in_currency": null,
      "price_change_percentage_7d_in_currency": null,
      "circulating_supply": 78597692029,
      "max_supply": 0,
      "description": null,
      "homepage": null,
      "explorer": null
    },
    {
      "id": "5663",
      "symbol": "sol",
      "name": "Solana",
      "market_cap_rank": 7,
      "image": null,
      "current_price": 106.23161282313612,
      "market_cap": 59785050435.559364,
      "total_volume": 1929902313.3675675,
      "price_change_percentage_1h_in_currency": null,
      "price_change_percentage_24h_in_currency": null,
      "price_change_percentage_7d_in_currency": null,
      "circulating_supply": 562780220,
      "max_supply": 0,
      "description": null,
      "homepage": null,
      "explorer": null
    },
    {
      "id": "13",
      "symbol": "trx",
      "name": "TRON",
      "market_cap_rank": 8,
      "image": null,
      "current_price": 0.23909831215166802,
      "market_cap": 22641063495.22992,
      "total_volume": 249142756.1577406,
      "price_change_percentage_1h_in_currency": null,
      "price_change_percentage_24h_in_currency": null,
      "price_change_percentage_7d_in_currency": null,
      "circulating_supply": 94693531257,
      "max_supply": 0,
      "description": null,
      "homepage": null,
      "explorer": null
    },
    {
      "id": "171882",
      "symbol": "steth",
      "name": "Lido Staked Ether",
      "market_cap_rank": 9,
      "image": null,
      "current_price": 2508.1019308177606,
      "market_cap": 22052325708.19159,
      "total_volume": 14868017.461049382,
      "price_change_percentage_1h_in_currency": null,
      "price_change_percentage_24h_in_currency": null,
      "price_change_percentage_7d_in_currency": null,
      "circulating_supply": 8792436,
      "max_supply": 0,
      "description": null,
      "homepage": null,
      "explorer": null
    },
    {
      "id": "41",
      "symbol": "doge",
      "name": "Dogecoin",
      "market_cap_rank": 10,
      "image": null,
      "current_price": 0.10626529760588006,
      "market_cap": 17860103477.026714,
      "total_volume": 459566928.2816761,
      "price_change_percentage_1h_in_currency": null,
      "price_change_percentage_24h_in_currency": null,
      "price_change_percentage_7d_in_currency": null,
      "circulating_supply": 168070893127,
      "max_supply": 0,
      "description": null,
      "homepage": null,
      "explorer": null
    },
    {
      "id": "7",
      "symbol": "ada",
      "name": "Cardano",
      "market_cap_rank": 11,
      "image": null,
      "current_price": 0.31415069404582874,
      "market_cap": 11517646406.40023,
      "total_volume": 303059467.39368135,
      "price_change_percentage_1h_in_currency": null,
      "price_change_percentage_24h_in_currency": null,
      "price_change_percentage_7d_in_currency": null,
      "circulating_supply": 36662807451,
      "max_supply": 45000000000,
      "description": null,
      "homepage": null,
      "explorer": null
    },
    {
      "id": "169760",
      "symbol": "wsteth",
      "name": "Wrapped stETH",
      "market_cap_rank": 101,
      "image": null,
      "current_price": 3071.2656854723978,
      "market_cap": 10338083000.835331,
      "total_volume": 4158287.3490755623,
      "price_change_percentage_1h_in_currency": null,
      "price_change_percentage_24h_in_currency": null,
      "price_change_percentage_7d_in_currency": null,
      "circulating_supply": 3366066,
      "max_supply": 0,
      "description": null,
      "homepage": null,
      "explorer": null
    },
    {
      "id": "9",
      "symbol": "bch",
      "name": "Bitcoin Cash",
      "market_cap_rank": 12,
      "image": null,
      "current_price": 512.2511999250504,
      "market_cap": 10231396579.829401,
      "total_volume": 233519916.75691926,
      "price_change_percentage_1h_in_currency": null,
      "price_change_percentage_24h_in_currency": null,
      "price_change_percentage_7d_in_currency": null,
      "circulating_supply": 19973397,
      "max_supply": 21000000,
      "description": null,
      "homepage": null,
      "explorer": null
    },
    {
      "id": "175850",
      "symbol": "wbt",
      "name": "WhiteBIT Coin",
      "market_cap_rank": 102,
      "image": null,
      "current_price": 47.363268948579375,
      "market_cap": 10141780124.227882,
      "total_volume": 28790220.881642245,
      "price_change_percentage_1h_in_currency": null,
      "price_change_percentage_24h_in_currency": null,
      "price_change_percentage_7d_in_currency": null,
      "circulating_supply": 214127537,
      "max_supply": 400000000,
      "description": null,
      "homepage": null,
      "explorer": null
    },
    {
      "id": "1883",
      "symbol": "wbtc",
      "name": "Wrapped Bitcoin",
      "market_cap_rank": 13,
      "image": null,
      "current_price": 74207.33140043385,
      "market_cap": 9273170753.792414,
      "total_volume": 189929612.99911594,
      "price_change_percentage_1h_in_currency": null,
      "price_change_percentage_24h_in_currency": null,
      "price_change_percentage_7d_in_currency": null,
      "circulating_supply": 124963,
      "max_supply": 129138,
      "description": null,
      "homepage": null,
      "explorer": null
    },
    {
      "id": "182647",
      "symbol": "wbeth",
      "name": "Wrapped Beacon ETH",
      "market_cap_rank": 103,
      "image": null,
      "current_price": 2729.6706528624945,
      "market_cap": 8911018035.28157,
      "total_volume": 19442461.92483865,
      "price_change_percentage_1h_in_currency": null,
      "price_change_percentage_24h_in_currency": null,
      "price_change_percentage_7d_in_currency": null,
      "circulating_supply": 3264503,
      "max_supply": 0,
      "description": null,
      "homepage": null,
      "explorer": null
    },
    {
      "id": "191826",
      "symbol": "usds",
      "name": "USDS",
      "market_cap_rank": 14,
      "image": null,
      "current_price": 0.836148835298626,
      "market_cap": 8332594815.252694,
      "total_volume": 24074309.175965946,
      "price_change_percentage_1h_in_currency": null,
      "price_change_percentage_24h_in_currency": null,
      "price_change_percentage_7d_in_currency": null,
      "circulating_supply": 9965444504,
      "max_supply": 0,
      "description": null,
      "homepage": null,
      "explorer": null
    },
    {
      "id": "186954",
      "symbol": "weeth",
      "name": "Wrapped eETH",
      "market_cap_rank": 15,
      "image": null,
      "current_price": 2721.4607918691627,
      "market_cap": 7703415903.759106,
      "total_volume": 1569382.0733863984,
      "price_change_percentage_1h_in_currency": null,
      "price_change_percentage_24h_in_currency": null,
      "price_change_percentage_7d_in_currency": null,
      "circulating_supply": 2830618,
      "max_supply": 0,
      "description": null,
      "homepage": null,
      "explorer": null
    },
    {
      "id": "85",
      "symbol": "link",
      "name": "ChainLink",
      "market_cap_rank": 16,
      "image": null,
      "current_price": 10.642023490407627,
      "market_cap": 7535616514.296937,
      "total_volume": 193951723.98859516,
      "price_change_percentage_1h_in_currency": null,
      "price_change_percentage_24h_in_currency": null,
      "price_change_percentage_7d_in_currency": null,
      "circulating_supply": 708099970,
      "max_supply": 1000000000,
      "description": null,
      "homepage": null,
      "explorer": null
    },
    {
      "id": "22",
      "symbol": "zec",
      "name": "Zcash",
      "market_cap_rank": 17,
      "image": null,
      "current_price": 443.18674393977756,
      "market_cap": 7230756149.659472,
      "total_volume": 481322210.8576602,
      "price_change_percentage_1h_in_currency": null,
      "price_change_percentage_24h_in_currency": null,
      "price_change_percentage_7d_in_currency": null,
      "circulating_supply": 16315371,
      "max_supply": 21000000,
      "description": null,
      "homepage": null,
      "explorer": null
    },
    {
      "id": "11",
      "symbol": "xmr",
      "name": "Monero",
      "market_cap_rank": 18,
      "image": null,
      "current_price": 378.4394182943405,
      "market_cap": 6980975068.7846155,
      "total_volume": 67251091.99757591,
      "price_change_percentage_1h_in_currency": null,
      "price_change_percentage_24h_in_currency": null,
      "price_change_percentage_7d_in_currency": null,
      "circulating_supply": 18446744,
      "max_supply": 0,
      "description": null,
      "homepage": null,
      "explorer": null
    },
    {
      "id": "7478",
      "symbol": "leo",
      "name": "UNUS SED LEO",
      "market_cap_rank": 104,
      "image": null,
      "current_price": 7.280613557731958,
      "market_cap": 6711016102.956306,
      "total_volume": 281262.0856251016,
      "price_change_percentage_1h_in_currency": null,
      "price_change_percentage_24h_in_currency": null,
      "price_change_percentage_7d_in_currency": null,
      "circulating_supply": 921765185,
      "max_supply": 1000000000,
      "description": null,
      "homepage": null,
      "explorer": null
    },
    {
      "id": "1254",
      "symbol": "weth",
      "name": "WETH",
      "market_cap_rank": 105,
      "image": null,
      "current_price": 2511.320484761637,
      "market_cap": 6510686252.961512,
      "total_volume": 733781310.2817123,
      "price_change_percentage_1h_in_currency": null,
      "price_change_percentage_24h_in_currency": null,
      "price_change_percentage_7d_in_currency": null,
      "circulating_supply": 2592535,
      "max_supply": 0,
      "description": null,
      "homepage": null,
      "explorer": null
    },
    {
      "id": "6",
      "symbol": "xlm",
      "name": "Stellar",
      "market_cap_rank": 19,
      "image": null,
      "current_price": 0.18754407116131475,
      "market_cap": 6078148063.410627,
      "total_volume": 72399063.07204314,
      "price_change_percentage_1h_in_currency": null,
      "price_change_percentage_24h_in_currency": null,
      "price_change_percentage_7d_in_currency": null,
      "circulating_supply": 32409172019,
      "max_supply": 50001786911,
      "description": null,
      "homepage": null,
      "explorer": null
    },
    {
      "id": "192087",
      "symbol": "cbbtc",
      "name": "Coinbase Wrapped BTC",
      "market_cap_rank": 106,
      "image": null,
      "current_price": 74369.59290537641,
      "market_cap": 5544848107.839055,
      "total_volume": 213664435.37388968,
      "price_change_percentage_1h_in_currency": null,
      "price_change_percentage_24h_in_currency": null,
      "price_change_percentage_7d_in_currency": null,
      "circulating_supply": 74558,
      "max_supply": 0,
      "description": null,
      "homepage": null,
      "explorer": null
    },
    {
      "id": "188967",
      "symbol": "usde",
      "name": "Ethena USDe",
      "market_cap_rank": 20,
      "image": null,
      "current_price": 0.8470834222651754,
      "market_cap": 5341007043.364766,
      "total_volume": 80797709.80096161,
      "price_change_percentage_1h_in_currency": null,
      "price_change_percentage_24h_in_currency": null,
      "price_change_percentage_7d_in_currency": null,
      "circulating_supply": 6305172434,
      "max_supply": 0,
      "description": null,
      "homepage": null,
      "explorer": null
    },
    {
      "id": "186323",
      "symbol": "hype",
      "name": "Hyperliquid",
      "market_cap_rank": 21,
      "image": null,
      "current_price": 21.72416370115697,
      "market_cap": 5178721628.736034,
      "total_volume": 127848777.54145887,
      "price_change_percentage_1h_in_currency": null,
      "price_change_percentage_24h_in_currency": null,
      "price_change_percentage_7d_in_currency": null,
      "circulating_supply": 238385316,
      "max_supply": 1000000000,
      "description": null,
      "homepage": null,
      "explorer": null
    },
    {
      "id": "8",
      "symbol": "ltc",
      "name": "Litecoin",
      "market_cap_rank": 22,
      "image": null,
      "current_price": 66.05955181040436,
      "market_cap": 5065167859.691822,
      "total_volume": 142973130.02735507,
      "price_change_percentage_1h_in_currency": null,
      "price_change_percentage_24h_in_currency": null,
      "price_change_percentage_7d_in_currency": null,
      "circulating_supply": 76675783,
      "max_supply": 84000000,
      "description": null,
      "homepage": null,
      "explorer": null
    },
    {
      "id": "175648",
      "symbol": "sui",
      "name": "Sui",
      "market_cap_rank": 23,
      "image": null,
      "current_price": 1.2430677388531326,
      "market_cap": 4645178017.764604,
      "total_volume": 363274540.03124255,
      "price_change_percentage_1h_in_currency": null,
      "price_change_percentage_24h_in_currency": null,
      "price_change_percentage_7d_in_currency": null,
      "circulating_supply": 3736866361,
      "max_supply": 10000000000,
      "description": null,
      "homepage": null,
      "explorer": null
    },
    {
      "id": "21076",
      "symbol": "avax",
      "name": "Avalanche",
      "market_cap_rank": 24,
      "image": null,
      "current_price": 10.796518802055338,
      "market_cap": 4638436576.077001,
      "total_volume": 186205127.31148612,
      "price_change_percentage_1h_in_currency": null,
      "price_change_percentage_24h_in_currency": null,
      "price_change_percentage_7d_in_currency": null,
      "circulating_supply": 429623350,
      "max_supply": 720000000,
      "description": null,
      "homepage": null,
      "explorer": null
    },
    {
      "id": "8491",
      "symbol": "hbar",
      "name": "Hedera",
      "market_cap_rank": 25,
      "image": null,
      "current_price": 0.09749155610830784,
      "market_cap": 4170367887.9705167,
      "total_volume": 65550298.861636385,
      "price_change_percentage_1h_in_currency": null,
      "price_change_percentage_24h_in_currency": null,
      "price_change_percentage_7d_in_currency": null,
      "circulating_supply": 42776708614,
      "max_supply": 50000000000,
      "description": null,
      "homepage": null,
      "explorer": null
    },
    {
      "id": "178101",
      "symbol": "cc",
      "name": "Canton Network",
      "market_cap_rank": 26,
      "image": null,
      "current_price": 0.10552203800170193,
      "market_cap": 3874706954.8383574,
      "total_volume": 40151829.64847796,
      "price_change_percentage_1h_in_currency": null,
      "price_change_percentage_24h_in_currency": null,
      "price_change_percentage_7d_in_currency": null,
      "circulating_supply": 36719409786,
      "max_supply": 0,
      "description": null,
      "homepage": null,
      "explorer": null
    },
    {
      "id": "21369",
      "symbol": "shib",
      "name": "SHIBA INU",
      "market_cap_rank": 27,
      "image": null,
      "current_price": 0.00000632826996528,
      "market_cap": 3728896651.712737,
      "total_volume": 34911577.67785501,
      "price_change_percentage_1h_in_currency": null,
      "price_change_percentage_24h_in_currency": null,
      "price_change_percentage_7d_in_currency": null,
      "circulating_supply": 589244244030564,
      "max_supply": 0,
      "description": null,
      "homepage": null,
      "explorer": null
    },
    {
      "id": "203800",
      "symbol": "susds",
      "name": "sUSDS",
      "market_cap_rank": 107,
      "image": null,
      "current_price": 0.9168705571618682,
      "market_cap": 3639298524.4197216,
      "total_volume": 5229873.175845299,
      "price_change_percentage_1h_in_currency": null,
      "price_change_percentage_24h_in_currency": null,
      "price_change_percentage_7d_in_currency": null,
      "circulating_supply": 3969260978,
      "max_supply": 0,
      "description": null,
      "homepage": null,
      "explorer": null
    },
    {
      "id": "19793",
      "symbol": "dai",
      "name": "Dai",
      "market_cap_rank": 28,
      "image": null,
      "current_price": 0.8479876708405291,
      "market_cap": 3610922789.8017855,
      "total_volume": 31813571.012540463,
      "price_change_percentage_1h_in_currency": null,
      "price_change_percentage_24h_in_currency": null,
      "price_change_percentage_7d_in_currency": null,
      "circulating_supply": 4258225578,
      "max_supply": 0,
      "description": null,
      "homepage": null,
      "explorer": null
    },
    {
      "id": "199041",
      "symbol": "usd₮0",
      "name": "USD₮0",
      "market_cap_rank": 108,
      "image": null,
      "current_price": 0.8475495384650057,
      "market_cap": 3605137510.968666,
      "total_volume": 36887666.40811474,
      "price_change_percentage_1h_in_currency": null,
      "price_change_percentage_24h_in_currency": null,
      "price_change_percentage_7d_in_currency": null,
      "circulating_supply": 4253600937,
      "max_supply": 0,
      "description": null,
      "homepage": null,
      "explorer": null
    },
    {
      "id": "160758",
      "symbol": "ton",
      "name": "Toncoin",
      "market_cap_rank": 29,
      "image": null,
      "current_price": 1.3798819352433642,
      "market_cap": 3385059785.6155276,
      "total_volume": 68618981.1315671,
      "price_change_percentage_1h_in_currency": null,
      "price_change_percentage_24h_in_currency": null,
      "price_change_percentage_7d_in_currency": null,
      "circulating_supply": 2453151751,
      "max_supply": 0,
      "description": null,
      "homepage": null,
      "explorer": null
    },
    {
      "id": "192343",
      "symbol": "wlfi",
      "name": "World Liberty Financial",
      "market_cap_rank": 30,
      "image": null,
      "current_price": 0.12256725529785938,
      "market_cap": 3339198100.9595156,
      "total_volume": 46762038.378026284,
      "price_change_percentage_1h_in_currency": null,
      "price_change_percentage_24h_in_currency": null,
      "price_change_percentage_7d_in_currency": null,
      "circulating_supply": 27243802538,
      "max_supply": 100000000000,
      "description": null,
      "homepage": null,
      "explorer": null
    },
    {
      "id": "185518",
      "symbol": "pyusd",
      "name": "PayPal USD",
      "market_cap_rank": 31,
      "image": null,
      "current_price": 0.84801896831074,
      "market_cap": 3323956291.2064104,
      "total_volume": 31932084.993183754,
      "price_change_percentage_1h_in_currency": null,
      "price_change_percentage_24h_in_currency": null,
      "price_change_percentage_7d_in_currency": null,
      "circulating_supply": 3919672101,
      "max_supply": 0,
      "description": null,
      "homepage": null,
      "explorer": null
    },
    {
      "id": "23857",
      "symbol": "uni",
      "name": "Uniswap",
      "market_cap_rank": 32,
      "image": null,
      "current_price": 5.189362374900655,
      "market_cap": 3268549974.5648656,
      "total_volume": 167015867.1905796,
      "price_change_percentage_1h_in_currency": null,
      "price_change_percentage_24h_in_currency": null,
      "price_change_percentage_7d_in_currency": null,
      "circulating_supply": 629855797,
      "max_supply": 0,
      "description": null,
      "homepage": null,
      "explorer": null
    },
    {
      "id": "5987",
      "symbol": "cro",
      "name": "Cronos",
      "market_cap_rank": 33,
      "image": null,
      "current_price": 0.07917352828463668,
      "market_cap": 3053859241.997144,
      "total_volume": 9498938.52163079,
      "price_change_percentage_1h_in_currency": null,
      "price_change_percentage_24h_in_currency": null,
      "price_change_percentage_7d_in_currency": null,
      "circulating_supply": 38571720980,
      "max_supply": 100000000000,
      "description": null,
      "homepage": null,
      "explorer": null
    },
    {
      "id": "182288",
      "symbol": "mnt",
      "name": "Mantle",
      "market_cap_rank": 34,
      "image": null,
      "current_price": 0.8822424785205903,
      "market_cap": 2970370773.2524176,
      "total_volume": 43604554.97320244,
      "price_change_percentage_1h_in_currency": null,
      "price_change_percentage_24h_in_currency": null,
      "price_change_percentage_7d_in_currency": null,
      "circulating_supply": 3366841708,
      "max_supply": 6219316795,
      "description": null,
      "homepage": null,
      "explorer": null
    },
    {
      "id": "190136",
      "symbol": "susde",
      "name": "Ethena Staked USDe",
      "market_cap_rank": 109,
      "image": null,
      "current_price": 1.0274376997706243,
      "market_cap": 2948725247.8595557,
      "total_volume": 7079224.405060919,
      "price_change_percentage_1h_in_currency": null,
      "price_change_percentage_24h_in_currency": null,
      "price_change_percentage_7d_in_currency": null,
      "circulating_supply": 2869979609,
      "max_supply": 0,
      "description": null,
      "homepage": null,
      "explorer": null
    },
    {
      "id": "199021",
      "symbol": "usd1",
      "name": "USD1",
      "market_cap_rank": 35,
      "image": null,
      "current_price": 0.8482559405198525,
      "market_cap": 2764370023.9625373,
      "total_volume": 608296922.8878278,
      "price_change_percentage_1h_in_currency": null,
      "price_change_percentage_24h_in_currency": null,
      "price_change_percentage_7d_in_currency": null,
      "circulating_supply": 3258886725,
      "max_supply": 0,
      "description": null,
      "homepage": null,
      "explorer": null
    },
    {
      "id": "22085",
      "symbol": "dot",
      "name": "Polkadot",
      "market_cap_rank": 36,
      "image": null,
      "current_price": 1.576336044119366,
      "market_cap": 2601013902.242153,
      "total_volume": 51541794.33327414,
      "price_change_percentage_1h_in_currency": null,
      "price_change_percentage_24h_in_currency": null,
      "price_change_percentage_7d_in_currency": null,
      "circulating_supply": 1650037701,
      "max_supply": 0,
      "description": null,
      "homepage": null,
      "explorer": null
    },
    {
      "id": "198370",
      "symbol": "rain",
      "name": "Rain",
      "market_cap_rank": 37,
      "image": null,
      "current_price": 0.00684676108483943,
      "market_cap": 2325237885.6565075,
      "total_volume": 43734627.9233035,
      "price_change_percentage_1h_in_currency": null,
      "price_change_percentage_24h_in_currency": null,
      "price_change_percentage_7d_in_currency": null,
      "circulating_supply": 339611366140,
      "max_supply": 1150000000000,
      "description": null,
      "homepage": null,
      "explorer": null
    },
    {
      "id": "198126",
      "symbol": "m",
      "name": "MemeCore",
      "market_cap_rank": 38,
      "image": null,
      "current_price": 1.2570128235402689,
      "market_cap": 2109903654.38018,
      "total_volume": 8663561.026952498,
      "price_change_percentage_1h_in_currency": null,
      "price_change_percentage_24h_in_currency": null,
      "price_change_percentage_7d_in_currency": null,
      "circulating_supply": 1678506070,
      "max_supply": 10000000000,
      "description": null,
      "homepage": null,
      "explorer": null
    },
    {
      "id": "179475",
      "symbol": "bgb",
      "name": "Bitget Token",
      "market_cap_rank": 39,
      "image": null,
      "current_price": 2.948847247263095,
      "market_cap": 2064169588.4646893,
      "total_volume": 78978285.0250169,
      "price_change_percentage_1h_in_currency": null,
      "price_change_percentage_24h_in_currency": null,
      "price_change_percentage_7d_in_currency": null,
      "circulating_supply": 699992036,
      "max_supply": 2000000000,
      "description": null,
      "homepage": null,
      "explorer": null
    },
    {
      "id": "23773",
      "symbol": "aave",
      "name": "Aave",
      "market_cap_rank": 40,
      "image": null,
      "current_price": 129.17109754687218,
      "market_cap": 1972325501.3552637,
      "total_volume": 92329495.20980038,
      "price_change_percentage_1h_in_currency": null,
      "price_change_percentage_24h_in_currency": null,
      "price_change_percentage_7d_in_currency": null,
      "circulating_supply": 15269093,
      "max_supply": 16000000,
      "description": null,
      "homepage": null,
      "explorer": null
    },
    {
      "id": "20048",
      "symbol": "xaut",
      "name": "Tether Gold",
      "market_cap_rank": 41,
      "image": null,
      "current_price": 3783.1714511556893,
      "market_cap": 1967585856.8601112,
      "total_volume": 128155630.52471454,
      "price_change_percentage_1h_in_currency": null,
      "price_change_percentage_24h_in_currency": null,
      "price_change_percentage_7d_in_currency": null,
      "circulating_supply": 520089,
      "max_supply": 0,
      "description": null,
      "homepage": null,
      "explorer": null
    },
    {
      "id": "1862",
      "symbol": "okb",
      "name": "OKB",
      "market_cap_rank": 42,
      "image": null,
      "current_price": 91.25296287531766,
      "market_cap": 1916312220.381671,
      "total_volume": 13203301.734024908,
      "price_change_percentage_1h_in_currency": null,
      "price_change_percentage_24h_in_currency": null,
      "price_change_percentage_7d_in_currency": null,
      "circulating_supply": 21000000,
      "max_supply": 300000000,
      "description": null,
      "homepage": null,
      "explorer": null
    },
    {
      "id": "200115",
      "symbol": "usdf",
      "name": "Falcon USD",
      "market_cap_rank": 110,
      "image": null,
      "current_price": 0.8464999013657685,
      "market_cap": 1835862279.0101905,
      "total_volume": 417793.4363592777,
      "price_change_percentage_1h_in_currency": null,
      "price_change_percentage_24h_in_currency": null,
      "price_change_percentage_7d_in_currency": null,
      "circulating_supply": 2168768450,
      "max_supply": 0,
      "description": null,
      "homepage": null,
      "explorer": null
    },
    {
      "id": "179365",
      "symbol": "tao",
      "name": "Bittensor",
      "market_cap_rank": 43,
      "image": null,
      "current_price": 188.62464899179224,
      "market_cap": 1810323371.076885,
      "total_volume": 50126267.30442061,
      "price_change_percentage_1h_in_currency": null,
      "price_change_percentage_24h_in_currency": null,
      "price_change_percentage_7d_in_currency": null,
      "circulating_supply": 9597491,
      "max_supply": 21000000,
      "description": null,
      "homepage": null,
      "explorer": null
    },
    {
      "id": "21422",
      "symbol": "near",
      "name": "Near Protocol",
      "market_cap_rank": 44,
      "image": null,
      "current_price": 1.3129286246921168,
      "market_cap": 1685445558.7765703,
      "total_volume": 70991884.75344414,
      "price_change_percentage_1h_in_currency": null,
      "price_change_percentage_24h_in_currency": null,
      "price_change_percentage_7d_in_currency": null,
      "circulating_supply": 1283729768,
      "max_supply": 0,
      "description": null,
      "homepage": null,
      "explorer": null
    },
    {
      "id": "14",
      "symbol": "etc",
      "name": "Ethereum Classic",
      "market_cap_rank": 45,
      "image": null,
      "current_price": 10.330321312639391,
      "market_cap": 1600255911.6704485,
      "total_volume": 16758401.87967825,
      "price_change_percentage_1h_in_currency": null,
      "price_change_percentage_24h_in_currency": null,
      "price_change_percentage_7d_in_currency": null,
      "circulating_supply": 154908629,
      "max_supply": 210700000,
      "description": null,
      "homepage": null,
      "explorer": null
    },
    {
      "id": "192002",
      "symbol": "lbtc",
      "name": "Lombard Staked BTC",
      "market_cap_rank": 111,
      "image": null,
      "current_price": 74526.23209665483,
      "market_cap": 1585098430.4637516,
      "total_volume": 1638898.9174143267,
      "price_change_percentage_1h_in_currency": null,
      "price_change_percentage_24h_in_currency": null,
      "price_change_percentage_7d_in_currency": null,
      "circulating_supply": 21269,
      "max_supply": 0,
      "description": null,
      "homepage": null,
      "explorer": null
    },
    {
      "id": "178752",
      "symbol": "jitosol",
      "name": "Jito Staked SOL",
      "market_cap_rank": 46,
      "image": null,
      "current_price": 132.99775531254414,
      "market_cap": 1515027038.9279218,
      "total_volume": 3086884.7368887723,
      "price_change_percentage_1h_in_currency": null,
      "price_change_percentage_24h_in_currency": null,
      "price_change_percentage_7d_in_currency": null,
      "circulating_supply": 11391373,
      "max_supply": 0,
      "description": null,
      "homepage": null,
      "explorer": null
    },
    {
      "id": "182292",
      "symbol": "pepe",
      "name": "Pepe",
      "market_cap_rank": 47,
      "image": null,
      "current_price": 0.0000035173231332,
      "market_cap": 1479702668.905908,
      "total_volume": 148084296.68349612,
      "price_change_percentage_1h_in_currency": null,
      "price_change_percentage_24h_in_currency": null,
      "price_change_percentage_7d_in_currency": null,
      "circulating_supply": 420690000000000,
      "max_supply": 420690000000000,
      "description": null,
      "homepage": null,
      "explorer": null
    },
    {
      "id": "187784",
      "symbol": "rseth",
      "name": "KelpDAO Restaked ETH",
      "market_cap_rank": 0,
      "image": null,
      "current_price": 2664.053545813948,
      "market_cap": 1463772212.908111,
      "total_volume": 1784.383064986182,
      "price_change_percentage_1h_in_currency": null,
      "price_change_percentage_24h_in_currency": null,
      "price_change_percentage_7d_in_currency": null,
      "circulating_supply": 549453,
      "max_supply": 0,
      "description": null,
      "homepage": null,
      "explorer": null
    },
    {
      "id": "195048",
      "symbol": "pi",
      "name": "Pi Network",
      "market_cap_rank": 48,
      "image": null,
      "current_price": 0.17286644819076982,
      "market_cap": 1447679412.5950615,
      "total_volume": 5866616.779220098,
      "price_change_percentage_1h_in_currency": null,
      "price_change_percentage_24h_in_currency": null,
      "price_change_percentage_7d_in_currency": null,
      "circulating_supply": 8374554043,
      "max_supply": 100000000000,
      "description": null,
      "homepage": null,
      "explorer": null
    },
    {
      "id": "191246",
      "symbol": "aster",
      "name": "Aster (prev. Astherus)",
      "market_cap_rank": 49,
      "image": null,
      "current_price": 0.5963114247048422,
      "market_cap": 1416263290.540841,
      "total_volume": 68061025.2102725,
      "price_change_percentage_1h_in_currency": null,
      "price_change_percentage_24h_in_currency": null,
      "price_change_percentage_7d_in_currency": null,
      "circulating_supply": 2375039672,
      "max_supply": 8000000000,
      "description": null,
      "homepage": null,
      "explorer": null
    },
    {
      "id": "90530",
      "symbol": "icp",
      "name": "Internet Computer",
      "market_cap_rank": 50,
      "image": null,
      "current_price": 2.586968430869327,
      "market_cap": 1412559829.3176112,
      "total_volume": 33638878.385004394,
      "price_change_percentage_1h_in_currency": null,
      "price_change_percentage_24h_in_currency": null,
      "price_change_percentage_7d_in_currency": null,
      "circulating_supply": 546029017,
      "max_supply": 0,
      "description": null,
      "homepage": null,
      "explorer": null
    },
    {
      "id": "185305",
      "symbol": "ena",
      "name": "Ethena",
      "market_cap_rank": 51,
      "image": null,
      "current_price": 0.17948376261666876,
      "market_cap": 1380342311.8738182,
      "total_volume": 86798636.98380941,
      "price_change_percentage_1h_in_currency": null,
      "price_change_percentage_24h_in_currency": null,
      "price_change_percentage_7d_in_currency": null,
      "circulating_supply": 7690625000,
      "max_supply": 0,
      "description": null,
      "homepage": null,
      "explorer": null
    },
    {
      "id": "8622",
      "symbol": "paxg",
      "name": "PAX Gold",
      "market_cap_rank": 52,
      "image": null,
      "current_price": 3792.738209262984,
      "market_cap": 1364414814.353103,
      "total_volume": 218714228.08893687,
      "price_change_percentage_1h_in_currency": null,
      "price_change_percentage_24h_in_currency": null,
      "price_change_percentage_7d_in_currency": null,
      "circulating_supply": 359744,
      "max_supply": 0,
      "description": null,
      "homepage": null,
      "explorer": null
    },
    {
      "id": "192947",
      "symbol": "usdg",
      "name": "Global Dollar",
      "market_cap_rank": 53,
      "image": null,
      "current_price": 0.8482786278750832,
      "market_cap": 1316091735.7762203,
      "total_volume": 4281625.572132272,
      "price_change_percentage_1h_in_currency": null,
      "price_change_percentage_24h_in_currency": null,
      "price_change_percentage_7d_in_currency": null,
      "circulating_supply": 1551485199,
      "max_supply": 0,
      "description": null,
      "homepage": null,
      "explorer": null
    },
    {
      "id": "203721",
      "symbol": "night",
      "name": "Midnight Network",
      "market_cap_rank": 54,
      "image": null,
      "current_price": 0.07788536557674201,
      "market_cap": 1293473373.6258514,
      "total_volume": 59771960.25997111,
      "price_change_percentage_1h_in_currency": null,
      "price_change_percentage_24h_in_currency": null,
      "price_change_percentage_7d_in_currency": null,
      "circulating_supply": 16607399401,
      "max_supply": 24000000000,
      "description": null,
      "homepage": null,
      "explorer": null
    },
    {
      "id": "201240",
      "symbol": "bfusd",
      "name": "BFUSD",
      "market_cap_rank": 112,
      "image": null,
      "current_price": 0.847205445319095,
      "market_cap": 1249628031.845665,
      "total_volume": 11102506.210528059,
      "price_change_percentage_1h_in_currency": null,
      "price_change_percentage_24h_in_currency": null,
      "price_change_percentage_7d_in_currency": null,
      "circulating_supply": 1475000000,
      "max_supply": 0,
      "description": null,
      "homepage": null,
      "explorer": null
    },
    {
      "id": "191825",
      "symbol": "sky",
      "name": "Sky",
      "market_cap_rank": 55,
      "image": null,
      "current_price": 0.052903257984180926,
      "market_cap": 1241251427.2681913,
      "total_volume": 12007702.565519989,
      "price_change_percentage_1h_in_currency": null,
      "price_change_percentage_24h_in_currency": null,
      "price_change_percentage_7d_in_currency": null,
      "circulating_supply": 23462665147,
      "max_supply": 0,
      "description": null,
      "homepage": null,
      "explorer": null
    },
    {
      "id": "195182",
      "symbol": "syrupusdc",
      "name": "SyrupUSDC",
      "market_cap_rank": 113,
      "image": null,
      "current_price": 0.9696580243947631,
      "market_cap": 1238897743.5110214,
      "total_volume": 582962.870026163,
      "price_change_percentage_1h_in_currency": null,
      "price_change_percentage_24h_in_currency": null,
      "price_change_percentage_7d_in_currency": null,
      "circulating_supply": 1277664612,
      "max_supply": 0,
      "description": null,
      "homepage": null,
      "explorer": null
    },
    {
      "id": "185400",
      "symbol": "fdusd",
      "name": "First Digital USD",
      "market_cap_rank": 56,
      "image": null,
      "current_price": 0.8465396230644687,
      "market_cap": 1229569979.5200548,
      "total_volume": 2474562210.9767847,
      "price_change_percentage_1h_in_currency": null,
      "price_change_percentage_24h_in_currency": null,
      "price_change_percentage_7d_in_currency": null,
      "circulating_supply": 1452465952,
      "max_supply": 0,
      "description": null,
      "homepage": null,
      "explorer": null
    },
    {
      "id": "190972",
      "symbol": "solvbtc",
      "name": "SolvBTC",
      "market_cap_rank": 0,
      "image": null,
      "current_price": 74306.35274246059,
      "market_cap": 1225386063.0759175,
      "total_volume": 33905.988756384766,
      "price_change_percentage_1h_in_currency": null,
      "price_change_percentage_24h_in_currency": null,
      "price_change_percentage_7d_in_currency": null,
      "circulating_supply": 16491,
      "max_supply": 21000000,
      "description": null,
      "homepage": null,
      "explorer": null
    },
    {
      "id": "60",
      "symbol": "kcs",
      "name": "KuCoin Token",
      "market_cap_rank": 57,
      "image": null,
      "current_price": 9.151104878446036,
      "market_cap": 1187592432.3416908,
      "total_volume": 1836682.3448115874,
      "price_change_percentage_1h_in_currency": null,
      "price_change_percentage_24h_in_currency": null,
      "price_change_percentage_7d_in_currency": null,
      "circulating_supply": 129775852,
      "max_supply": 200000000,
      "description": null,
      "homepage": null,
      "explorer": null
    },
    {
      "id": "190497",
      "symbol": "rlusd",
      "name": "Ripple USD",
      "market_cap_rank": 58,
      "image": null,
      "current_price": 0.8480921632971259,
      "market_cap": 1151905214.6152549,
      "total_volume": 9422461.851112105,
      "price_change_percentage_1h_in_currency": null,
      "price_change_percentage_24h_in_currency": null,
      "price_change_percentage_7d_in_currency": null,
      "circulating_supply": 1358231174,
      "max_supply": 0,
      "description": null,
      "homepage": null,
      "explorer": null
    },
    {
      "id": "25781",
      "symbol": "wbnb",
      "name": "Wrapped BNB",
      "market_cap_rank": 114,
      "image": null,
      "current_price": 724.4977348117611,
      "market_cap": 1104021526.2064934,
      "total_volume": 481663569.7127202,
      "price_change_percentage_1h_in_currency": null,
      "price_change_percentage_24h_in_currency": null,
      "price_change_percentage_7d_in_currency": null,
      "circulating_supply": 1523844,
      "max_supply": 0,
      "description": null,
      "homepage": null,
      "explorer": null
    },
    {
      "id": "174670",
      "symbol": "apt",
      "name": "Aptos",
      "market_cap_rank": 59,
      "image": null,
      "current_price": 1.4678167430392857,
      "market_cap": 1101152423.1976964,
      "total_volume": 44876171.24499455,
      "price_change_percentage_1h_in_currency": null,
      "price_change_percentage_24h_in_currency": null,
      "price_change_percentage_7d_in_currency": null,
      "circulating_supply": 750197481,
      "max_supply": 0,
      "description": null,
      "homepage": null,
      "explorer": null
    },
    {
      "id": "192098",
      "symbol": "bnsol",
      "name": "Binance Staked SOL",
      "market_cap_rank": 115,
      "image": null,
      "current_price": 115.85150945469483,
      "market_cap": 1087416559.7885642,
      "total_volume": 7563384.1803843025,
      "price_change_percentage_1h_in_currency": null,
      "price_change_percentage_24h_in_currency": null,
      "price_change_percentage_7d_in_currency": null,
      "circulating_supply": 9386296,
      "max_supply": 0,
      "description": null,
      "homepage": null,
      "explorer": null
    },
    {
      "id": "171101",
      "symbol": "reth",
      "name": "Rocket Pool ETH",
      "market_cap_rank": 116,
      "image": null,
      "current_price": 2897.5823573899397,
      "market_cap": 1042350199.0062404,
      "total_volume": 978704.5127679345,
      "price_change_percentage_1h_in_currency": null,
      "price_change_percentage_24h_in_currency": null,
      "price_change_percentage_7d_in_currency": null,
      "circulating_supply": 359731,
      "max_supply": 0,
      "description": null,
      "homepage": null,
      "explorer": null
    },
    {
      "id": "174378",
      "symbol": "ondo",
      "name": "Ondo Finance",
      "market_cap_rank": 60,
      "image": null,
      "current_price": 0.3274710117163153,
      "market_cap": 1034516138.642259,
      "total_volume": 26153917.00376559,
      "price_change_percentage_1h_in_currency": null,
      "price_change_percentage_24h_in_currency": null,
      "price_change_percentage_7d_in_currency": null,
      "circulating_supply": 3159107529,
      "max_supply": 10000000000,
      "description": null,
      "homepage": null,
      "explorer": null
    },
    {
      "id": "7139",
      "symbol": "gt",
      "name": "GateToken",
      "market_cap_rank": 61,
      "image": null,
      "current_price": 8.719871078625086,
      "market_cap": 1023228685.0690736,
      "total_volume": 2280385.342844551,
      "price_change_percentage_1h_in_currency": null,
      "price_change_percentage_24h_in_currency": null,
      "price_change_percentage_7d_in_currency": null,
      "circulating_supply": 117344474,
      "max_supply": 0,
      "description": null,
      "homepage": null,
      "explorer": null
    },
    {
      "id": "174899",
      "symbol": "kas",
      "name": "Kaspa",
      "market_cap_rank": 62,
      "image": null,
      "current_price": 0.03756324207355793,
      "market_cap": 1005836515.3146284,
      "total_volume": 9784396.806188297,
      "price_change_percentage_1h_in_currency": null,
      "price_change_percentage_24h_in_currency": null,
      "price_change_percentage_7d_in_currency": null,
      "circulating_supply": 26777148611,
      "max_supply": 28704026601,
      "description": null,
      "homepage": null,
      "explorer": null
    },
    {
      "id": "178389",
      "symbol": "wld",
      "name": "World",
      "market_cap_rank": 63,
      "image": null,
      "current_price": 0.43041137321804535,
      "market_cap": 971885832.908692,
      "total_volume": 45881393.73291682,
      "price_change_percentage_1h_in_currency": null,
      "price_change_percentage_24h_in_currency": null,
      "price_change_percentage_7d_in_currency": null,
      "circulating_supply": 2258039386,
      "max_supply": 10000000000,
      "description": null,
      "homepage": null,
      "explorer": null
    },
    {
      "id": "186232",
      "symbol": "pol",
      "name": "POL (ex-MATIC)",
      "market_cap_rank": 64,
      "image": null,
      "current_price": 0.09068254537686458,
      "market_cap": 957989391.5756911,
      "total_volume": 27131601.80417904,
      "price_change_percentage_1h_in_currency": null,
      "price_change_percentage_24h_in_currency": null,
      "price_change_percentage_7d_in_currency": null,
      "circulating_supply": 10564209326,
      "max_supply": 0,
      "description": null,
      "homepage": null,
      "explorer": null
    },
    {
      "id": "175987",
      "symbol": "arb",
      "name": "Arbitrum",
      "market_cap_rank": 65,
      "image": null,
      "current_price": 0.16398453463173157,
      "market_cap": 937874513.9740398,
      "total_volume": 38858616.43426869,
      "price_change_percentage_1h_in_currency": null,
      "price_change_percentage_24h_in_currency": null,
      "price_change_percentage_7d_in_currency": null,
      "circulating_supply": 5719286371,
      "max_supply": 10000000000,
      "description": null,
      "homepage": null,
      "explorer": null
    },
    {
      "id": "191834",
      "symbol": "pump",
      "name": "pump.fun",
      "market_cap_rank": 66,
      "image": null,
      "current_price": 0.0015868216627212299,
      "market_cap": 936224781.0055258,
      "total_volume": 40395131.13996863,
      "price_change_percentage_1h_in_currency": null,
      "price_change_percentage_24h_in_currency": null,
      "price_change_percentage_7d_in_currency": null,
      "circulating_supply": 590000000000,
      "max_supply": 1000000000000,
      "description": null,
      "homepage": null,
      "explorer": null
    },
    {
      "id": "3475",
      "symbol": "qnt",
      "name": "Quant",
      "market_cap_rank": 67,
      "image": null,
      "current_price": 61.177982685040334,
      "market_cap": 889783347.4961792,
      "total_volume": 5408571.079698168,
      "price_change_percentage_1h_in_currency": null,
      "price_change_percentage_24h_in_currency": null,
      "price_change_percentage_7d_in_currency": null,
      "circulating_supply": 14544176,
      "max_supply": 14612493,
      "description": null,
      "homepage": null,
      "explorer": null
    },
    {
      "id": "5551",
      "symbol": "algo",
      "name": "Algorand",
      "market_cap_rank": 68,
      "image": null,
      "current_price": 0.10056059109047297,
      "market_cap": 888546550.8894212,
      "total_volume": 13624291.245342385,
      "price_change_percentage_1h_in_currency": null,
      "price_change_percentage_24h_in_currency": null,
      "price_change_percentage_7d_in_currency": null,
      "circulating_supply": 8835932061,
      "max_supply": 10000000000,
      "description": null,
      "homepage": null,
      "explorer": null
    },
    {
      "id": "200541",
      "symbol": "khype",
      "name": "Kinetiq Staked HYPE",
      "market_cap_rank": 117,
      "image": null,
      "current_price": 21.994147118254226,
      "market_cap": 881118964.660884,
      "total_volume": 3301542.1365315085,
      "price_change_percentage_1h_in_currency": null,
      "price_change_percentage_24h_in_currency": null,
      "price_change_percentage_7d_in_currency": null,
      "circulating_supply": 40061520,
      "max_supply": 0,
      "description": null,
      "homepage": null,
      "explorer": null
    },
    {
      "id": "187892",
      "symbol": "ezeth",
      "name": "Renzo Restaked ETH",
      "market_cap_rank": 118,
      "image": null,
      "current_price": 2681.0814499661064,
      "market_cap": 865504032.5966086,
      "total_volume": 176296.92371582633,
      "price_change_percentage_1h_in_currency": null,
      "price_change_percentage_24h_in_currency": null,
      "price_change_percentage_7d_in_currency": null,
      "circulating_supply": 322819,
      "max_supply": 0,
      "description": null,
      "homepage": null,
      "explorer": null
    },
    {
      "id": "194453",
      "symbol": "trump",
      "name": "OFFICIAL TRUMP",
      "market_cap_rank": 69,
      "image": null,
      "current_price": 4.206348454640379,
      "market_cap": 841269577.3566675,
      "total_volume": 62785625.840037085,
      "price_change_percentage_1h_in_currency": null,
      "price_change_percentage_24h_in_currency": null,
      "price_change_percentage_7d_in_currency": null,
      "circulating_supply": 199999973,
      "max_supply": 1000000000,
      "description": null,
      "homepage": null,
      "explorer": null
    },
    {
      "id": "26233",
      "symbol": "fil",
      "name": "Filecoin",
      "market_cap_rank": 70,
      "image": null,
      "current_price": 1.1502508342493278,
      "market_cap": 839348450.4232895,
      "total_volume": 78995974.38757473,
      "price_change_percentage_1h_in_currency": null,
      "price_change_percentage_24h_in_currency": null,
      "price_change_percentage_7d_in_currency": null,
      "circulating_supply": 729709056,
      "max_supply": 1959845164,
      "description": null,
      "homepage": null,
      "explorer": null
    },
    {
      "id": "6834",
      "symbol": "atom",
      "name": "Cosmos Hub",
      "market_cap_rank": 71,
      "image": null,
      "current_price": 1.7280227266728467,
      "market_cap": 838716245.251159,
      "total_volume": 17492547.38976487,
      "price_change_percentage_1h_in_currency": null,
      "price_change_percentage_24h_in_currency": null,
      "price_change_percentage_7d_in_currency": null,
      "circulating_supply": 485361814,
      "max_supply": 0,
      "description": null,
      "homepage": null,
      "explorer": null
    },
    {
      "id": "2056",
      "symbol": "xdc",
      "name": "XDC Network",
      "market_cap_rank": 72,
      "image": null,
      "current_price": 0.04427863243062192,
      "market_cap": 820347234.0573287,
      "total_volume": 21862594.866137102,
      "price_change_percentage_1h_in_currency": null,
      "price_change_percentage_24h_in_currency": null,
      "price_change_percentage_7d_in_currency": null,
      "circulating_supply": 18526932496,
      "max_supply": 0,
      "description": null,
      "homepage": null,
      "explorer": null
    },
    {
      "id": "2208",
      "symbol": "vet",
      "name": "VeChain",
      "market_cap_rank": 73,
      "image": null,
      "current_price": 0.009496295911341488,
      "market_cap": 816539394.9656748,
      "total_volume": 10332744.59264946,
      "price_change_percentage_1h_in_currency": null,
      "price_change_percentage_24h_in_currency": null,
      "price_change_percentage_7d_in_currency": null,
      "circulating_supply": 85985041177,
      "max_supply": 86712634466,
      "description": null,
      "homepage": null,
      "explorer": null
    },
    {
      "id": "179864",
      "symbol": "flr",
      "name": "Flare",
      "market_cap_rank": 74,
      "image": null,
      "current_price": 0.00952313780186007,
      "market_cap": 767275790.8038983,
      "total_volume": 2870535.1323093213,
      "price_change_percentage_1h_in_currency": null,
      "price_change_percentage_24h_in_currency": null,
      "price_change_percentage_7d_in_currency": null,
      "circulating_supply": 80569640676,
      "max_supply": 0,
      "description": null,
      "homepage": null,
      "explorer": null
    },
    {
      "id": "2132",
      "symbol": "nexo",
      "name": "Nexo",
      "market_cap_rank": 75,
      "image": null,
      "current_price": 0.7625857616482852,
      "market_cap": 762585761.6482853,
      "total_volume": 5847563.862239109,
      "price_change_percentage_1h_in_currency": null,
      "price_change_percentage_24h_in_currency": null,
      "price_change_percentage_7d_in_currency": null,
      "circulating_supply": 1000000000,
      "max_supply": 1000000000,
      "description": null,
      "homepage": null,
      "explorer": null
    },
    {
      "id": "174427",
      "symbol": "usdd",
      "name": "USDD",
      "market_cap_rank": 76,
      "image": null,
      "current_price": 0.8472545931583938,
      "market_cap": 690936038.5369745,
      "total_volume": 4075019.182565137,
      "price_change_percentage_1h_in_currency": null,
      "price_change_percentage_24h_in_currency": null,
      "price_change_percentage_7d_in_currency": null,
      "circulating_supply": 815499903,
      "max_supply": 0,
      "description": null,
      "homepage": null,
      "explorer": null
    },
    {
      "id": "189437",
      "symbol": "jupsol",
      "name": "Jupiter Staked SOL",
      "market_cap_rank": 119,
      "image": null,
      "current_price": 123.27656112240318,
      "market_cap": 671092943.4381384,
      "total_volume": 176448.81152086763,
      "price_change_percentage_1h_in_currency": null,
      "price_change_percentage_24h_in_currency": null,
      "price_change_percentage_7d_in_currency": null,
      "circulating_supply": 5443800,
      "max_supply": 0,
      "description": null,
      "homepage": null,
      "explorer": null
    },
    {
      "id": "175979",
      "symbol": "sei",
      "name": "Sei",
      "market_cap_rank": 77,
      "image": null,
      "current_price": 0.09680584887993762,
      "market_cap": 628377521.27435,
      "total_volume": 23736528.59923084,
      "price_change_percentage_1h_in_currency": null,
      "price_change_percentage_24h_in_currency": null,
      "price_change_percentage_7d_in_currency": null,
      "circulating_supply": 6491111111,
      "max_supply": 0,
      "description": null,
      "homepage": null,
      "explorer": null
    },
    {
      "id": "5857",
      "symbol": "bdx",
      "name": "Beldex",
      "market_cap_rank": 78,
      "image": null,
      "current_price": 0.08222867872815932,
      "market_cap": 614888198.4734114,
      "total_volume": 5410435.755163878,
      "price_change_percentage_1h_in_currency": null,
      "price_change_percentage_24h_in_currency": null,
      "price_change_percentage_7d_in_currency": null,
      "circulating_supply": 7477782788,
      "max_supply": 0,
      "description": null,
      "homepage": null,
      "explorer": null
    },
    {
      "id": "186857",
      "symbol": "meth",
      "name": "Mantle Staked Ether",
      "market_cap_rank": 79,
      "image": null,
      "current_price": 2745.3204235261405,
      "market_cap": 591377708.3930365,
      "total_volume": 1451301.2879551882,
      "price_change_percentage_1h_in_currency": null,
      "price_change_percentage_24h_in_currency": null,
      "price_change_percentage_7d_in_currency": null,
      "circulating_supply": 215413,
      "max_supply": 0,
      "description": null,
      "homepage": null,
      "explorer": null
    }
  ]
}