{
  "id": 1785,
  "rank": 196,
  "name": "Gas",
  "symbol": "GAS",
  "price": 2.1090411103881466,
  "change1h": -0.05869061,
  "change24h": -0.64925119,
  "change7d": 5.10149463,
  "market_cap": 137071497.93895397,
  "volume_24h": 17210794.35476486,
  "circulating_supply": 64992331,
  "max_supply": null,
  "sparkline7d": [],
  "description": "Gas (GAS) is a cryptocurrency and operates on the Neo platform. Gas has a current supply of 64,992,331. The last known price of Gas is 2.10804204 USD and is down -0.14 over the last 24 hours. It is currently trading on 178 active market(s) with $17,227,553.16 traded over the last 24 hours. More information can be found at https://neo.org/.",
  "logo": "https://s2.coinmarketcap.com/static/img/coins/64x64/1785.png",
  "urls": {
    "website": [
      "https://neo.org/"
    ],
    "twitter": [
      "https://twitter.com/Neo_Blockchain"
    ],
    "message_board": [],
    "chat": [
      "https://t.me/NEO_EN",
      "https://discord.com/invite/neosmarteconomy"
    ],
    "facebook": [],
    "explorer": [
      "https://xexplorer.neo.org/address/0xdE41591ED1f8ED1484aC2CD8ca0876428de60EfF",
      "https://dora.coz.io/",
      "https://explorer.onegate.space/homepage",
      "https://neo3.neotube.io/",
      "https://neoxscan.ngd.network/"
    ],
    "reddit": [],
    "technical_doc": [
      "http://docs.neo.org/en-us/"
    ],
    "source_code": [],
    "announcement": []
  },
  "tags": []
}