{
  "id": "2087",
  "symbol": "KCS",
  "name": "KuCoin Token",
  "slug": "kucoin-token",
  "rank": 50,
  "price": 11.200127467853928,
  "marketCap": 1480153088.9553585,
  "volume24h": 2342065.10082032,
  "circulating": 132155021.73556715,
  "totalSupply": 142155021.73556715,
  "maxSupply": 200000000,
  "percentChange1h": -0.08297147,
  "percentChange24h": 1.0517733,
  "percentChange7d": 4.17725077,
  "lastUpdated": "2026-01-05T12:53:00.000Z",
  "logo": "https://s2.coinmarketcap.com/static/img/coins/64x64/2087.png",
  "tags": [
    "marketplace",
    "centralized-exchange",
    "discount-token",
    "ethereum-ecosystem",
    "made-in-china"
  ],
  "category": "token",
  "platform": {
    "id": "1027",
    "name": "Ethereum",
    "slug": "ethereum",
    "symbol": "ETH",
    "token_address": "0xf34960d9d60be18cc1d5afc1a6f012a723a28811"
  },
  "selfReportedCirculatingSupply": null,
  "selfReportedMarketCap": null,
  "geckoId": "kucoin-shares"
}