{
  "id": "36462",
  "symbol": "A",
  "name": "Vaulta",
  "slug": "vaulta",
  "rank": 138,
  "price": 0.17811208905183504,
  "marketCap": 287512411.3157033,
  "volume24h": 20390604.18058414,
  "circulating": 1614221768.1363,
  "totalSupply": 2100000000,
  "maxSupply": 2100000000,
  "percentChange1h": 0.2524014,
  "percentChange24h": 2.85880775,
  "percentChange7d": 13.48591225,
  "lastUpdated": "2026-01-04T23:41:00.000Z",
  "logo": "https://s2.coinmarketcap.com/static/img/coins/64x64/36462.png",
  "tags": [
    "medium-of-exchange",
    "enterprise-solutions",
    "defi",
    "smart-contracts",
    "eos-ecosystem",
    "fenbushi-capital-portfolio",
    "galaxy-digital-portfolio",
    "dwf-labs-portfolio",
    "2017-2018-alt-season",
    "made-in-america",
    "binance-ecosystem",
    "binance-listing",
    "wlfi-ecosystem"
  ],
  "category": "coin",
  "platform": {
    "id": "36462",
    "name": "Vaulta",
    "slug": "vaulta",
    "symbol": "A",
    "token_address": "core.vaulta"
  },
  "selfReportedCirculatingSupply": 1562570047.65,
  "selfReportedMarketCap": 278312615.47676694,
  "geckoId": "vaulta"
}